ckanext_datagovcatalog-0.1.3-nspkg.pth
ckanext/datagovcatalog/__init__.py
ckanext/datagovcatalog/plugin.py
ckanext/datagovcatalog/harvester/__init__.py
ckanext/datagovcatalog/harvester/notifications.py
ckanext/datagovcatalog/helpers/__init__.py
ckanext/datagovcatalog/helpers/packages.py
ckanext/datagovcatalog/tests/__init__.py
ckanext/datagovcatalog/tests/test_before_view.py
ckanext/datagovcatalog/tests/test_notifications.py
ckanext/datagovcatalog/tests/test_package_list.py
ckanext/datagovcatalog/tests/test_plugin.py
ckanext_datagovcatalog-0.1.3.dist-info/LICENSE
ckanext_datagovcatalog-0.1.3.dist-info/METADATA
ckanext_datagovcatalog-0.1.3.dist-info/WHEEL
ckanext_datagovcatalog-0.1.3.dist-info/entry_points.txt
ckanext_datagovcatalog-0.1.3.dist-info/namespace_packages.txt
ckanext_datagovcatalog-0.1.3.dist-info/top_level.txt
ckanext_datagovcatalog-0.1.3.dist-info/RECORD
