Metadata-Version: 2.1
Name: ckanext-datagovcatalog
Version: 0.1.3
Summary: Catalog customizations
Home-page: https://github.com/GSA/ckanext-datagovcatalog
Author: Data.gov
Author-email: datagovhelp@gsa.gov
License: AGPL
Keywords: CKAN
Classifier: Development Status :: 4 - Beta
Classifier: License :: OSI Approved :: GNU Affero General Public License v3 or later (AGPLv3+)
Classifier: Programming Language :: Python :: 3
License-File: LICENSE
